spacename/__init__.py
spacename-1.0.1.dist-info/LICENSE
spacename-1.0.1.dist-info/METADATA
spacename-1.0.1.dist-info/WHEEL
spacename-1.0.1.dist-info/RECORD
