Metadata-Version: 2.1
Name: spacename
Version: 1.0.1
Summary: An alternative to dictionaries, built on the argparse Namespace class.
Home-page: https://github.com/tinkering-townsperson/spacename
License: MIT
Author: AfterNoonPM
Author-email: h2o.Drop2010+pypi@gmail.com
Requires-Python: >=3.8.1,<4.0.0
Classifier: Intended Audience :: Developers
Classifier: License :: OSI Approved :: MIT License
Classifier: Operating System :: OS Independent
Classifier: Programming Language :: Python :: 3
Classifier: Programming Language :: Python :: 3.9
Classifier: Programming Language :: Python :: 3.10
Classifier: Programming Language :: Python :: 3.11
Classifier: Programming Language :: Python :: 3.8
Classifier: Programming Language :: Python :: Implementation :: CPython
Project-URL: Bug Tracker, https://github.com/tinkering-townsperson/spacename/issues
Project-URL: Repository, https://github.com/tinkering-townsperson/spacename
